bitget_sdk/__init__.py
bitget_sdk/__init__.pyi
bitget_sdk/core.py
bitget_sdk/reporting/__init__.py
bitget_sdk/reporting/snapshots.py
bitget_sdk/reporting/transactions/__init__.py
bitget_sdk/reporting/transactions/futures.py
bitget_sdk/reporting/transactions/internal_transfers.py
bitget_sdk/reporting/transactions/margin.py
bitget_sdk/reporting/transactions/spot.py
bitget_sdk/reporting/transactions/transactions.py
bitget_trading_sdk-0.1.3.dist-info/METADATA
bitget_trading_sdk-0.1.3.dist-info/WHEEL
bitget_trading_sdk-0.1.3.dist-info/top_level.txt
bitget_trading_sdk-0.1.3.dist-info/RECORD
