Metadata-Version: 2.4
Name: bitget-trading-sdk
Version: 0.1.3
Summary: Tribulnation SDK implementation for Bitget.
Author-email: Marcel Claramunt <marcel@tribulnation.com>
Project-URL: repo, https://github.com/tribulnation/sdk.git
Requires-Python: >=3.10
Requires-Dist: typed-bitget
